lightning_tutorial/__init__.py
lightning_tutorial/_data/__init__.py
lightning_tutorial/_data/_pbmc3k_adata.py
lightning_tutorial-0.0.2.dist-info/LICENSE
lightning_tutorial-0.0.2.dist-info/METADATA
lightning_tutorial-0.0.2.dist-info/WHEEL
lightning_tutorial-0.0.2.dist-info/top_level.txt
lightning_tutorial-0.0.2.dist-info/RECORD
