Metadata-Version: 2.1
Name: lightning-tutorial
Version: 0.0.2
Summary: pytorch-lightning tutorial
Home-page: https://github.com/mvinyard/vinplots
Author: Michael E. Vinyard - Harvard University - Massachussetts General Hospital - Broad Institute of MIT and Harvard
Author-email: mvinyard@broadinstitute.org
License: MIT
Classifier: Development Status :: 2 - Pre-Alpha
Classifier: Programming Language :: Python :: 3.7
Classifier: Intended Audience :: Science/Research
Classifier: Topic :: Scientific/Engineering :: Bio-Informatics
Requires-Python: >3.7.0
License-File: LICENSE
Requires-Dist: torch (>=1.12.1)
Requires-Dist: pytorch-lightning (>=1.7.4)
Requires-Dist: scanpy (>=1.9.1)
Requires-Dist: nb-black (>=0.7)
Requires-Dist: torch-adata (>=0.0.12)
Requires-Dist: vinplots (>=0.0.72)
Requires-Dist: torch-composer (>=0.0.3)
Requires-Dist: larry-dataset (>=0.0.1)
